{"chunk_definitions":[{"chunk_id":"cbtf4ycfyg19g","chunk_label":"unnamed-chunk-2","document_id":"3BCCD000","expansion_state":0,"options":{"engine":"r","label":"unnamed-chunk-1"},"row":59,"row_count":1,"visible":true},{"chunk_id":"cz6fh93nlddde","chunk_label":"unnamed-chunk-3","document_id":"3BCCD000","expansion_state":0,"options":{"engine":"r","label":"unnamed-chunk-2"},"row":66,"row_count":1,"visible":true},{"chunk_id":"c14sffpcc2nkk","chunk_label":"unnamed-chunk-5","document_id":"3BCCD000","expansion_state":0,"options":{"engine":"r","label":"unnamed-chunk-6"},"row":83,"row_count":1,"visible":true},{"chunk_id":"cn2i4kusgedwi","chunk_label":"unnamed-chunk-7","document_id":"3BCCD000","expansion_state":0,"options":{"engine":"r","label":"unnamed-chunk-42"},"row":146,"row_count":1,"visible":true}],"doc_write_time":1573019640}